cs_mcp/__about__.py
cs_mcp/__init__.py
cs_mcp/__main__.py
cs_mcp/server.py
cs_mcp/configs/__init__.py
cs_mcp/configs/config.py
cs_mcp/constants/__init__.py
cs_mcp/constants/ldl_constants.py
cs_mcp/db/dependencies.py
cs_mcp/db/models/__init__.py
cs_mcp/db/models/base.py
cs_mcp/db/models/ltcdrglist.py
cs_mcp/db/models/ns.py
cs_mcp/db/models/progressnote.py
cs_mcp/db/models/table_manager.py
cs_mcp/db/models/vs.py
cs_mcp/db/models/wj.py
cs_mcp/db/models/jinryo/jy.py
cs_mcp/db/services/ltcdrg_service.py
cs_mcp/db/sqlalchemy/__init__.py
cs_mcp/db/sqlalchemy/map.py
cs_mcp/libs/__init__.py
cs_mcp/libs/temp_dict.py
cs_mcp/tools/__init__.py
cs_mcp/tools/advice_tools.py
cs_mcp/tools/jy_tools.py
cs_mcp/tools/ltcdrglist_tools.py
cs_mcp/tools/ns_tools.py
cs_mcp/tools/patient_info_tools.py
cs_mcp/tools/progress_note_tools.py
cs_mcp/tools/util_tools.py
cs_mcp/tools/vs_tools.py
cs_mcp/tools/args/vs_args.py
cs_mcp/tools/types/__init__.py
cs_mcp/tools/types/tool_types.py
cs_mcp/utils/__init__.py
cs_mcp/utils/pipe_client.py
cs_mcp-0.0.12.dist-info/METADATA
cs_mcp-0.0.12.dist-info/WHEEL
cs_mcp-0.0.12.dist-info/entry_points.txt
cs_mcp-0.0.12.dist-info/licenses/LICENSE.txt
cs_mcp-0.0.12.dist-info/RECORD
