Metadata-Version: 2.4
Name: cs-mcp
Version: 0.0.12
Project-URL: Documentation, https://github.com/Kaburi/hatch-test#readme
Project-URL: Issues, https://github.com/Kaburi/hatch-test/issues
Project-URL: Source, https://github.com/Kaburi/hatch-test
Author-email: Kaburi <specialemail90@gmail.com>
License-Expression: MIT
License-File: LICENSE.txt
Classifier: Development Status :: 4 - Beta
Classifier: Programming Language :: Python
Classifier: Programming Language :: Python :: 3.13
Classifier: Programming Language :: Python :: Implementation :: CPython
Classifier: Programming Language :: Python :: Implementation :: PyPy
Requires-Python: >=3.13
Requires-Dist: aiomysql>=0.2.0
Requires-Dist: fastmcp>=2.11.3
Requires-Dist: greenlet>=3.2.4
Requires-Dist: mcp[cli]>=1.6.0
Requires-Dist: pandas>=2.2.3
Requires-Dist: sqlalchemy>=2.0.40
Requires-Dist: tabulate>=0.9.0
Requires-Dist: twine>=6.2.0
